{"api.md":"BP7svzGn","changelog.md":"DDxEJTUv","ecosystem.md":"OqEztXB7","explanations_animation.md":"FCSi7Bqs","explanations_backends_backends.md":"DHBGs5Qi","explanations_backends_cairomakie.md":"DO1Fug-k","explanations_backends_glmakie.md":"CVInRbuD","explanations_backends_rprmakie.md":"DBL_4vCl","explanations_backends_wglmakie.md":"Dn5YE8wg","explanations_blocks.md":"DZVfq-ko","explanations_cameras.md":"nZBZyG4e","explanations_colors.md":"wXkGMtz3","explanations_conversion_pipeline.md":"y0uxG7wm","explanations_dim-converts.md":"CptV2MR9","explanations_events.md":"B9uWmxR-","explanations_faq.md":"DcLdVOMk","explanations_figure.md":"BWluIgrH","explanations_fonts.md":"CVOooZ78","explanations_headless.md":"k0M5xkXR","explanations_inspector.md":"BIbzPHkb","explanations_latex.md":"B4rLHMPU","explanations_layouting.md":"C-hJ2Hfh","explanations_observables.md":"DDzTcdyo","explanations_plot_method_signatures.md":"jQYsItHf","explanations_recipes.md":"DDdF65ib","explanations_scenes.md":"CFf0L8iD","explanations_specapi.md":"DsNtMj64","explanations_theming_predefined_themes.md":"C2jEfVlp","explanations_theming_themes.md":"DlXE4Rot","explanations_transparency.md":"DEooV14u","how-to_draw-boxes-around-subfigures.md":"BGAR6dG_","how-to_match-figure-size-font-sizes-and-dpi.md":"OVCm96yH","how-to_save-figure-with-transparency.md":"FLLJvAYH","index.md":"CwC0CL_X","reference_blocks_axis.md":"DH-rVbGb","reference_blocks_axis3.md":"Bd2jL8Ti","reference_blocks_box.md":"DgArrzYA","reference_blocks_button.md":"B4r4321j","reference_blocks_checkbox.md":"aVRMizQc","reference_blocks_colorbar.md":"BjJrmTFP","reference_blocks_gridlayout.md":"DW9spLES","reference_blocks_intervalslider.md":"DdiM8jt6","reference_blocks_label.md":"BWhEX8dZ","reference_blocks_legend.md":"BmpHPmGo","reference_blocks_lscene.md":"Q8OKovsJ","reference_blocks_menu.md":"erhloDN6","reference_blocks_overview.md":"CIgs2Uwi","reference_blocks_polaraxis.md":"DuCSsjrB","reference_blocks_slider.md":"DR9veS8K","reference_blocks_slidergrid.md":"BdLkuCBG","reference_blocks_textbox.md":"BBzY-JyG","reference_blocks_toggle.md":"C-3xsZce","reference_plots_ablines.md":"LOqWtlPj","reference_plots_arc.md":"Bdj4yMFm","reference_plots_arrows.md":"C7svEQJl","reference_plots_band.md":"x40O24xn","reference_plots_barplot.md":"CUx-MwKe","reference_plots_boxplot.md":"DahcGmIk","reference_plots_bracket.md":"B71bzsq4","reference_plots_contour.md":"B24NK4r4","reference_plots_contour3d.md":"DK-9h-YF","reference_plots_contourf.md":"CsvTzQjL","reference_plots_crossbar.md":"HZHDgZNp","reference_plots_datashader.md":"DUEfLODe","reference_plots_density.md":"wWC0VQ_T","reference_plots_ecdf.md":"C3rqEKwR","reference_plots_errorbars.md":"CRP6D4MO","reference_plots_heatmap.md":"B8PXxKFS","reference_plots_hexbin.md":"CwCyNeON","reference_plots_hist.md":"CNE7HsE4","reference_plots_hlines.md":"CDyQODTd","reference_plots_hspan.md":"Ckqmyh79","reference_plots_image.md":"H0WHSV7d","reference_plots_lines.md":"TgHEP2u_","reference_plots_linesegments.md":"DbrABp7j","reference_plots_mesh.md":"Js2ssWUv","reference_plots_meshscatter.md":"CTuwDq_c","reference_plots_overview.md":"CeDaQN3P","reference_plots_pie.md":"CaXbT7K6","reference_plots_poly.md":"BvV0cbPW","reference_plots_qqnorm.md":"D05ev6ip","reference_plots_qqplot.md":"B7KC5Yy6","reference_plots_rainclouds.md":"CM6UjP_l","reference_plots_rangebars.md":"_VeZyVnH","reference_plots_scatter.md":"C6pw2Tbi","reference_plots_scatterlines.md":"BqnrZeJ-","reference_plots_series.md":"Bo1L9zna","reference_plots_spy.md":"CtS7sEvO","reference_plots_stairs.md":"BHwVaul4","reference_plots_stem.md":"DHjyWo3V","reference_plots_stephist.md":"C0rW_I6W","reference_plots_streamplot.md":"DCuYz1QN","reference_plots_surface.md":"BVmDd57v","reference_plots_text.md":"BJ8-4i7D","reference_plots_tooltip.md":"CYTW5NEo","reference_plots_tricontourf.md":"CHkfmS_Z","reference_plots_triplot.md":"UezaIOd2","reference_plots_violin.md":"CE8bIhxB","reference_plots_vlines.md":"B3xcIY4q","reference_plots_volume.md":"xgBfJrsl","reference_plots_volumeslices.md":"DvuZCvOo","reference_plots_voronoiplot.md":"CkAmdfHb","reference_plots_voxels.md":"D762Qvd4","reference_plots_vspan.md":"B0kf7-P7","reference_plots_waterfall.md":"TvDiBvqv","reference_plots_wireframe.md":"BeCwFQe5","reference_scene_clip_planes.md":"DIVrRp8E","reference_scene_lighting.md":"BwDwDHxu","reference_scene_matcap.md":"Co0gasGR","reference_scene_ssao.md":"k19-qynn","tutorials_aspect-tutorial.md":"Che1fl_t","tutorials_getting-started.md":"YbD_Cshr","tutorials_layout-tutorial.md":"DMogF6mX","tutorials_scenes.md":"91yfT_8I","tutorials_wrap-existing-recipe.md":"CLQmbqDk"}
