{"api.md":"UfSKao89","changelog.md":"Ck_ONyNn","ecosystem.md":"DIytccBr","explanations_animation.md":"DakExWnL","explanations_architecture.md":"x-XD1Wxk","explanations_backends_backends.md":"D7JaB5ux","explanations_backends_cairomakie.md":"Bsq5dPfm","explanations_backends_glmakie.md":"D9Gd4J5g","explanations_backends_rprmakie.md":"BHs2HAnU","explanations_backends_wglmakie.md":"BU5ODfyR","explanations_blocks.md":"BkhSoGak","explanations_cameras.md":"QV_CFYUi","explanations_colors.md":"Bo-_O7Cr","explanations_compute-pipeline.md":"Ckx5kh79","explanations_conversion_pipeline.md":"hh0tIiA-","explanations_dim-converts.md":"DwEkZUN5","explanations_events.md":"DQKQvDjP","explanations_faq.md":"DcZHfa2q","explanations_figure.md":"DU6nNriU","explanations_fonts.md":"DIBx8t21","explanations_headless.md":"C8XCpbq0","explanations_inspector.md":"c6gV5sao","explanations_latex.md":"BxLyNMst","explanations_layouting.md":"DNM6i4wL","explanations_observables.md":"BEzt8ZMX","explanations_plot_method_signatures.md":"Dhd5V_KO","explanations_recipes.md":"3Ja16xKM","explanations_scenes.md":"C0r9fLU0","explanations_specapi.md":"syi-Escb","explanations_theming_predefined_themes.md":"CPmFueG1","explanations_theming_themes.md":"DLdJmIZd","explanations_transformations.md":"DAq7dtzO","explanations_transparency.md":"Ctww_QEb","how-to_draw-boxes-around-subfigures.md":"B3LaTDK5","how-to_match-figure-size-font-sizes-and-dpi.md":"L5bl1aDp","how-to_save-figure-with-transparency.md":"CLLwhO93","index.md":"g0CvPTwT","reference_blocks_axis.md":"Daz3Nx7B","reference_blocks_axis3.md":"DmlnCmQM","reference_blocks_box.md":"D571vwqF","reference_blocks_button.md":"Dv3z-hKX","reference_blocks_checkbox.md":"wLnYF9pO","reference_blocks_colorbar.md":"eGU8he0T","reference_blocks_gridlayout.md":"DboDtMX7","reference_blocks_intervalslider.md":"D_ETWfn3","reference_blocks_label.md":"XnNzHeP3","reference_blocks_legend.md":"DrOgyAhn","reference_blocks_lscene.md":"s4B9phXz","reference_blocks_menu.md":"rsxVy3j8","reference_blocks_overview.md":"CL_WifWW","reference_blocks_polaraxis.md":"CNAilzD_","reference_blocks_slider.md":"Db6E0Mvl","reference_blocks_slidergrid.md":"F8V610HQ","reference_blocks_textbox.md":"CNGWU5-F","reference_blocks_toggle.md":"BWqvzqY2","reference_generic_clip_planes.md":"DE2g-3a_","reference_generic_space.md":"C4ck7Imh","reference_generic_transformations.md":"Btf5e5KX","reference_plots_ablines.md":"Cznawykj","reference_plots_annotation.md":"TJEAsZDV","reference_plots_arc.md":"DLwt3d8d","reference_plots_arrows.md":"Cd29MtQk","reference_plots_band.md":"O61lkIvN","reference_plots_barplot.md":"DdNbZUeO","reference_plots_boxplot.md":"mtyRI64D","reference_plots_bracket.md":"C505-Nhb","reference_plots_contour.md":"rHn6ENhH","reference_plots_contour3d.md":"B-T5BCF5","reference_plots_contourf.md":"BH2rNNmK","reference_plots_crossbar.md":"BveSM6Dz","reference_plots_datashader.md":"Dr5F1ubo","reference_plots_dendrogram.md":"BHjR5RSI","reference_plots_density.md":"DkqdFNrO","reference_plots_ecdf.md":"Ci9rwuMX","reference_plots_errorbars.md":"ma30z0rh","reference_plots_heatmap.md":"DQTsffgO","reference_plots_hexbin.md":"DF9V0r06","reference_plots_hist.md":"CL8onQtB","reference_plots_hlines.md":"CbdAbzdo","reference_plots_hspan.md":"lU6Mge1O","reference_plots_image.md":"B5mEKhKR","reference_plots_lines.md":"Cs6SZXK7","reference_plots_linesegments.md":"C-iSQoTK","reference_plots_mesh.md":"guSXCf7k","reference_plots_meshscatter.md":"DF1_asGC","reference_plots_overview.md":"VnUTo6dP","reference_plots_pie.md":"7lvp3x8l","reference_plots_poly.md":"3vqRJPSQ","reference_plots_qqnorm.md":"DwYEtOHS","reference_plots_qqplot.md":"CbTii3hi","reference_plots_rainclouds.md":"CaN2gOGF","reference_plots_rangebars.md":"DMkZHqhB","reference_plots_scatter.md":"B0gQffkr","reference_plots_scatterlines.md":"COOmMAz0","reference_plots_series.md":"DV-3p6rb","reference_plots_spy.md":"CXfHXZ3W","reference_plots_stairs.md":"ChCypval","reference_plots_stem.md":"CFCv75J4","reference_plots_stephist.md":"CkJQWiZt","reference_plots_streamplot.md":"CfpDgCA0","reference_plots_surface.md":"DbNuaWy6","reference_plots_text.md":"BT6uvgaA","reference_plots_textlabel.md":"CPVmUFwW","reference_plots_tooltip.md":"DYdh7yKC","reference_plots_tricontourf.md":"B4S-hM4U","reference_plots_triplot.md":"Cx8lFtfF","reference_plots_violin.md":"Cp1VUwv8","reference_plots_vlines.md":"Cu3zGM1a","reference_plots_volume.md":"C5eSuWLZ","reference_plots_volumeslices.md":"CALWEhfR","reference_plots_voronoiplot.md":"C6p3p6w5","reference_plots_voxels.md":"CqvnNPr0","reference_plots_vspan.md":"3w0MLPY-","reference_plots_waterfall.md":"fMFbj1b1","reference_plots_wireframe.md":"ChnXZ2_B","reference_scene_lighting.md":"DgDphH3m","reference_scene_matcap.md":"DZ_nHhco","reference_scene_ssao.md":"Bojxpqzp","tutorials_aspect-tutorial.md":"vS6uTkNU","tutorials_getting-started.md":"QdAcfDiI","tutorials_inset-plot-tutorial.md":"C8hIJ8QM","tutorials_layout-tutorial.md":"DgvIRo7t","tutorials_pixel-perfect-rendering.md":"DI4IHt-J","tutorials_scenes.md":"a6vZgxKU","tutorials_wrap-existing-recipe.md":"DiyawV9I"}
