{"api.md":"D5MhCU-e","changelog.md":"C3sR4vEE","ecosystem.md":"DliBwdA0","explanations_animation.md":"CuBD8mow","explanations_backends_backends.md":"BR6hnhQO","explanations_backends_cairomakie.md":"Bmgihxiu","explanations_backends_glmakie.md":"DfhcTqgk","explanations_backends_rprmakie.md":"CKvWPk2a","explanations_backends_wglmakie.md":"Cmet5z8-","explanations_blocks.md":"BIE5VW7p","explanations_cameras.md":"M3vo6DYB","explanations_colors.md":"BjMXMPmU","explanations_compute-pipeline.md":"Dna03LO3","explanations_conversion_pipeline.md":"cPMdEszM","explanations_dim-converts.md":"Az0Sozg-","explanations_events.md":"WKz_z59H","explanations_faq.md":"qb6L4THi","explanations_figure.md":"WwazKSlA","explanations_fonts.md":"Ds59sso-","explanations_headless.md":"C--YQUl-","explanations_inspector.md":"DTEBFQ-a","explanations_latex.md":"3E4dPyNp","explanations_layouting.md":"CaitYOMn","explanations_observables.md":"DxnQqgVN","explanations_plot_method_signatures.md":"CWNSYKw4","explanations_recipes.md":"erC2WJEy","explanations_scenes.md":"BJs77UHW","explanations_specapi.md":"DtcFlYyC","explanations_theming_predefined_themes.md":"BdtzfoiH","explanations_theming_themes.md":"DBi-ScHB","explanations_transparency.md":"BF0yDizl","how-to_draw-boxes-around-subfigures.md":"Dp4YV22M","how-to_match-figure-size-font-sizes-and-dpi.md":"53DCvfjS","how-to_save-figure-with-transparency.md":"DoFQIfjD","index.md":"QUcP9853","reference_blocks_axis.md":"By1g71mU","reference_blocks_axis3.md":"3at6YO9n","reference_blocks_box.md":"D9pJI0lL","reference_blocks_button.md":"DZ4UahaR","reference_blocks_checkbox.md":"BcIhD9EK","reference_blocks_colorbar.md":"DJIhLgbU","reference_blocks_gridlayout.md":"B4FP5D8T","reference_blocks_intervalslider.md":"Do5HbEaq","reference_blocks_label.md":"C3qbqUWO","reference_blocks_legend.md":"CWcIwrk4","reference_blocks_lscene.md":"ChY9cn9r","reference_blocks_menu.md":"8I_oxX6-","reference_blocks_overview.md":"f4b1E0B6","reference_blocks_polaraxis.md":"B1iqvsd3","reference_blocks_slider.md":"B011YWOF","reference_blocks_slidergrid.md":"BhFJhQF6","reference_blocks_textbox.md":"D53FpVro","reference_blocks_toggle.md":"gRrITw_f","reference_generic_clip_planes.md":"D9MLJGVW","reference_generic_space.md":"fyevwpBw","reference_generic_transformations.md":"C5df4DHp","reference_plots_ablines.md":"B-rDa9bW","reference_plots_annotation.md":"BJ8ibeb2","reference_plots_arc.md":"FXiXj1od","reference_plots_arrows.md":"D7RB6gKQ","reference_plots_band.md":"VgQ_8hXu","reference_plots_barplot.md":"UzTQzGKd","reference_plots_boxplot.md":"D2rwkVeF","reference_plots_bracket.md":"ByD6rdg0","reference_plots_contour.md":"CBXTqoK5","reference_plots_contour3d.md":"DS1ifQta","reference_plots_contourf.md":"uMFqwmqw","reference_plots_crossbar.md":"BNi1POf1","reference_plots_datashader.md":"C72fdIrm","reference_plots_dendrogram.md":"CSwMCBFm","reference_plots_density.md":"CZmojfQr","reference_plots_ecdf.md":"CQEZhI1G","reference_plots_errorbars.md":"kNu-ro4J","reference_plots_heatmap.md":"CMsOqQz-","reference_plots_hexbin.md":"BtwQ1zX1","reference_plots_hist.md":"rGgll9ya","reference_plots_hlines.md":"CfA4hQ9l","reference_plots_hspan.md":"ChCZS8Q-","reference_plots_image.md":"DxP7fFbN","reference_plots_lines.md":"XTTe_7MP","reference_plots_linesegments.md":"D1PgdUmy","reference_plots_mesh.md":"wOWy-rg9","reference_plots_meshscatter.md":"BqFDBtwx","reference_plots_overview.md":"v7wr-OHl","reference_plots_pie.md":"B2YWLQv3","reference_plots_poly.md":"CLBY0Rev","reference_plots_qqnorm.md":"GtXPad0d","reference_plots_qqplot.md":"D5gLeRD4","reference_plots_rainclouds.md":"O_e8o5wx","reference_plots_rangebars.md":"DYESIIcI","reference_plots_scatter.md":"Bd5KzQNz","reference_plots_scatterlines.md":"BQA-g8T3","reference_plots_series.md":"CwSG609i","reference_plots_spy.md":"CsYGlEm9","reference_plots_stairs.md":"Cbu-X3g2","reference_plots_stem.md":"BRmeSOD8","reference_plots_stephist.md":"D1dGfL7m","reference_plots_streamplot.md":"B_d0fDsU","reference_plots_surface.md":"DGvn4wlE","reference_plots_text.md":"CxlhN0ED","reference_plots_textlabel.md":"CK8rx0Sn","reference_plots_tooltip.md":"CnWHOQh_","reference_plots_tricontourf.md":"CF0dMr3s","reference_plots_triplot.md":"COBPCTbI","reference_plots_violin.md":"DID9czwT","reference_plots_vlines.md":"D7JSncdd","reference_plots_volume.md":"CE4axdYC","reference_plots_volumeslices.md":"DYk3odUV","reference_plots_voronoiplot.md":"BMN8eYpR","reference_plots_voxels.md":"D6dNHuHD","reference_plots_vspan.md":"hu2uQvio","reference_plots_waterfall.md":"aWsg-RjI","reference_plots_wireframe.md":"D58YTF5C","reference_scene_lighting.md":"B759r3-k","reference_scene_matcap.md":"BLo0kYkb","reference_scene_ssao.md":"BEl0od1U","tutorials_aspect-tutorial.md":"CltTQ0aI","tutorials_getting-started.md":"B-nYCkto","tutorials_inset-plot-tutorial.md":"-9lcV670","tutorials_layout-tutorial.md":"BDT0m75b","tutorials_pixel-perfect-rendering.md":"DqRVly8J","tutorials_scenes.md":"D3tGqjdL","tutorials_wrap-existing-recipe.md":"B9nmyxgD"}
