{"api.md":"Dg_kPNJj","changelog.md":"_Q_9EDmD","ecosystem.md":"Bdi2yLTw","explanations_animation.md":"CEebh9EA","explanations_backends_backends.md":"3j4lrd1i","explanations_backends_cairomakie.md":"B44yz04V","explanations_backends_glmakie.md":"CBplkbTy","explanations_backends_rprmakie.md":"Bw9mfirf","explanations_backends_wglmakie.md":"BQuYkFwo","explanations_blocks.md":"DLFCnr34","explanations_cameras.md":"D6OXjhV6","explanations_colors.md":"hcC2ajM6","explanations_conversion_pipeline.md":"BkqljbWo","explanations_dim-converts.md":"D8Qv_viG","explanations_events.md":"DyuvfcDv","explanations_faq.md":"D1tuaa7M","explanations_figure.md":"y2bFrqLS","explanations_fonts.md":"Cb8Mqn0A","explanations_headless.md":"ftQ1m18d","explanations_inspector.md":"CYQ5qrJC","explanations_latex.md":"uT5wlYHZ","explanations_layouting.md":"C2fCxs4O","explanations_observables.md":"LTo_fMdS","explanations_plot_method_signatures.md":"Fu9Rqhum","explanations_recipes.md":"BDwBACQa","explanations_scenes.md":"Ce9lOwed","explanations_specapi.md":"CWhnxrlP","explanations_theming_predefined_themes.md":"CxIGU1EJ","explanations_theming_themes.md":"BPFasgRM","explanations_transparency.md":"DBxxeIFU","how-to_draw-boxes-around-subfigures.md":"DadTLoP-","how-to_match-figure-size-font-sizes-and-dpi.md":"C4A-n5Lp","how-to_save-figure-with-transparency.md":"BOmp-lYi","index.md":"C8OJ81qF","reference_blocks_axis.md":"5lm1OZYL","reference_blocks_axis3.md":"D2T9IR9o","reference_blocks_box.md":"A-STZj5p","reference_blocks_button.md":"DhgpTuLn","reference_blocks_checkbox.md":"CZEv7Y2u","reference_blocks_colorbar.md":"DJDUh-C1","reference_blocks_gridlayout.md":"DkmnmsGy","reference_blocks_intervalslider.md":"vuZtiHsp","reference_blocks_label.md":"InJFt0Fw","reference_blocks_legend.md":"YevKq2H8","reference_blocks_lscene.md":"HKhBZGpP","reference_blocks_menu.md":"BPLoait6","reference_blocks_overview.md":"BP316FVc","reference_blocks_polaraxis.md":"Dd39t9f1","reference_blocks_slider.md":"C6EcITG1","reference_blocks_slidergrid.md":"BTFz8if6","reference_blocks_textbox.md":"DI3J_BNJ","reference_blocks_toggle.md":"CK_ZzlJW","reference_generic_clip_planes.md":"D02AaIkg","reference_generic_space.md":"CCU23IjY","reference_generic_transformations.md":"DFM39Na3","reference_plots_ablines.md":"ukm127Ah","reference_plots_arc.md":"DT_33_5k","reference_plots_arrows.md":"BNB6HkbL","reference_plots_band.md":"Eyb7tjiw","reference_plots_barplot.md":"DKBm9xob","reference_plots_boxplot.md":"eru1Mx_k","reference_plots_bracket.md":"DFyLJc2S","reference_plots_contour.md":"i3kmqo1E","reference_plots_contour3d.md":"B-xgA0Xe","reference_plots_contourf.md":"BPrlGz4h","reference_plots_crossbar.md":"DrOkQpdU","reference_plots_datashader.md":"CxN5SgZJ","reference_plots_density.md":"BwK0XqM5","reference_plots_ecdf.md":"BwnUFiMt","reference_plots_errorbars.md":"CC2GWMIl","reference_plots_heatmap.md":"DIvX2SSt","reference_plots_hexbin.md":"BJzas7QV","reference_plots_hist.md":"BHrcpGBw","reference_plots_hlines.md":"BTo0GTMF","reference_plots_hspan.md":"CHZWS_lw","reference_plots_image.md":"ChHJTWHP","reference_plots_lines.md":"C6tKoW2a","reference_plots_linesegments.md":"CcF3WitR","reference_plots_mesh.md":"DOj2ASpR","reference_plots_meshscatter.md":"BKvlDMyo","reference_plots_overview.md":"BTEVlk24","reference_plots_pie.md":"DbGnzJan","reference_plots_poly.md":"DjznaGY-","reference_plots_qqnorm.md":"Dmh76g5h","reference_plots_qqplot.md":"BRXpEQCg","reference_plots_rainclouds.md":"CsgdMB_m","reference_plots_rangebars.md":"BQkV8Ijy","reference_plots_scatter.md":"C4-OZJtB","reference_plots_scatterlines.md":"ot7aCL8R","reference_plots_series.md":"Z4-uTrLi","reference_plots_spy.md":"Cr7c1AuY","reference_plots_stairs.md":"T6UmugJY","reference_plots_stem.md":"CwUsFtwV","reference_plots_stephist.md":"DOgTaMjW","reference_plots_streamplot.md":"DYXU95Pp","reference_plots_surface.md":"CVrwzZJJ","reference_plots_text.md":"D2Tgd1An","reference_plots_textlabel.md":"CMJD8b1h","reference_plots_tooltip.md":"QuxwMJlY","reference_plots_tricontourf.md":"kCQvB1LT","reference_plots_triplot.md":"BxNsiUW5","reference_plots_violin.md":"ByRmeeSC","reference_plots_vlines.md":"BfQ7brlI","reference_plots_volume.md":"BKPGvYhF","reference_plots_volumeslices.md":"x66wnOQ3","reference_plots_voronoiplot.md":"syKBAB2W","reference_plots_voxels.md":"CrktZ63-","reference_plots_vspan.md":"ChdhybZZ","reference_plots_waterfall.md":"BCbfzrpl","reference_plots_wireframe.md":"DQilrUBw","reference_scene_lighting.md":"DLSCn8BK","reference_scene_matcap.md":"BUoOystq","reference_scene_ssao.md":"CNCOYaAL","tutorials_aspect-tutorial.md":"CWt7yq4z","tutorials_getting-started.md":"TkLMN8kf","tutorials_inset-plot-tutorial.md":"iyPVVS1V","tutorials_layout-tutorial.md":"-jD_xccB","tutorials_pixel-perfect-rendering.md":"BmQoxtc3","tutorials_scenes.md":"DgbFNJ2W","tutorials_wrap-existing-recipe.md":"BPmtfMkB"}
